bj_led/__init__.py
bj_led/manager.py
bj_led/scanner.py
bj_led/uuid_scanner.py
gui/__init__.py
gui/app.py
BJ_LED_M-0.1.dist-info/METADATA
BJ_LED_M-0.1.dist-info/WHEEL
BJ_LED_M-0.1.dist-info/entry_points.txt
BJ_LED_M-0.1.dist-info/top_level.txt
BJ_LED_M-0.1.dist-info/RECORD
