Metadata-Version: 2.1
Name: BJ_LED_M
Version: 0.1
Summary: A library for controlling MohuanLED lights via Bluetooth
Author: Walkercito
Author-email: walkercitoliver@gmail.com
Classifier: Programming Language :: Python :: 3
Classifier: License :: OSI Approved :: MIT License
Classifier: Operating System :: OS Independent
Classifier: Operating System :: Microsoft :: Windows
Classifier: Operating System :: POSIX :: Linux
Classifier: Operating System :: MacOS
Requires-Python: >=3.8
Requires-Dist: bleak
Requires-Dist: qasync
Requires-Dist: PyQt6
Requires-Dist: python-dotenv
